nvpy/__init__.py
nvpy/__main__.py
nvpy/bindings.py
nvpy/debug.py
nvpy/events.py
nvpy/notes_db.py
nvpy/nvpy-example.cfg
nvpy/nvpy.py
nvpy/search_entry.py
nvpy/tk.py
nvpy/utils.py
nvpy/version.py
nvpy/view.py
nvpy/vxlabs-nvpy.desktop
nvpy/icons/README.md
nvpy/icons/nvpy.gif
nvpy/icons/nvpy.icns
nvpy/icons/nvpy.ico
nvpy/icons/nvpy_icon_256x256.png
nvpy-2.3.1.dist-info/LICENSE.txt
nvpy-2.3.1.dist-info/METADATA
nvpy-2.3.1.dist-info/WHEEL
nvpy-2.3.1.dist-info/entry_points.txt
nvpy-2.3.1.dist-info/top_level.txt
nvpy-2.3.1.dist-info/RECORD
