Metadata-Version: 2.1
Name: nvpy
Version: 2.3.1
Summary: A cross-platform simplenote-syncing note-taking app inspired by Notational Velocity.
Home-page: https://github.com/cpbotha/nvpy
Author: Charl P. Botha
Author-email: cpbotha@vxlabs.com
Maintainer: yuuki0xff
Maintainer-email: yuuki0xff@gmail.com
License: BSD
Keywords: simplenote note-taking tkinter nvalt markdown
Classifier: Development Status :: 5 - Production/Stable
Classifier: Environment :: X11 Applications
Classifier: Environment :: MacOS X
Classifier: Environment :: Win32 (MS Windows)
Classifier: Programming Language :: Python :: 3
Classifier: Programming Language :: Python :: 3.6
Classifier: Programming Language :: Python :: 3.7
Classifier: Programming Language :: Python :: 3.8
Classifier: Programming Language :: Python :: 3.9
Classifier: Programming Language :: Python :: 3.10
Classifier: Programming Language :: Python :: 3.11
Classifier: Topic :: Utilities
Classifier: License :: OSI Approved :: BSD License
License-File: LICENSE.txt
Requires-Dist: Markdown
Requires-Dist: docutils
Requires-Dist: simplenote >=2.1.4
Provides-Extra: dev
Requires-Dist: mock ; extra == 'dev'
Requires-Dist: yapf ; extra == 'dev'
Requires-Dist: pdoc3 ; extra == 'dev'
Requires-Dist: mypy ; extra == 'dev'
Requires-Dist: coverage ; extra == 'dev'
Requires-Dist: types-Markdown ; extra == 'dev'
Requires-Dist: types-certifi ; extra == 'dev'
Requires-Dist: types-docutils ; extra == 'dev'
Requires-Dist: types-mock ; extra == 'dev'
